setup.py
mllog/__init__.py
mllog/mllog.py
mllog.egg-info/PKG-INFO
mllog.egg-info/SOURCES.txt
mllog.egg-info/dependency_links.txt
mllog.egg-info/requires.txt
mllog.egg-info/top_level.txt