Metadata-Version: 1.0
Name: mllog
Version: 0.0.4
Summary: mllog
Home-page: https://mllog.com
Author: mllog
Author-email: mllog@mllog.com
License: MIT
Platform: UNKNOWN
